verilog/manufacturing_fsm.v
module manufacturing_fsm (
    input wire clk,
    input wire rst,
    input wire metal_detected,
    input wire high_temp, 
    input wire overcurrent,
    input wire error,
    input wire done,
    input wire ready,
    input wire temp_normal,
    input wire reset_btn,
    input wire emergency,
    output reg conveyor,
    output reg servo,
    output reg fan,
    output reg warning_light,
    output reg buzzer,
    output reg valve
);

// State encoding
localparam [2:0] 
    IDLE           = 3'b000,
    NORMAL_OP      = 3'b001,
    METAL_HANDLING = 3'b010,
    RETURN_NORMAL  = 3'b011,
    COOLING_ACTIVE = 3'b100,
    EMERGENCY_STOP = 3'b101;

reg [2:0] current_state, next_state;

// State transition logic
always @(*) begin
    case (current_state)
        IDLE: begin
            if (emergency) next_state = EMERGENCY_STOP;
            else next_state = NORMAL_OP;
        end
        
        NORMAL_OP: begin
            if (emergency || overcurrent) next_state = EMERGENCY_STOP;
            else if (metal_detected) next_state = METAL_HANDLING;
            else if (high_temp) next_state = COOLING_ACTIVE;
            else next_state = NORMAL_OP;
        end
        
        METAL_HANDLING: begin
            if (emergency || error) next_state = EMERGENCY_STOP;
            else if (high_temp) next_state = COOLING_ACTIVE;
            else if (done) next_state = RETURN_NORMAL;
            else next_state = METAL_HANDLING;
        end
        
        RETURN_NORMAL: begin
            if (emergency) next_state = EMERGENCY_STOP;
            else if (high_temp) next_state = COOLING_ACTIVE;
            else if (ready) next_state = NORMAL_OP;
            else next_state = RETURN_NORMAL;
        end
        
        COOLING_ACTIVE: begin
            if (emergency) next_state = EMERGENCY_STOP;
            else if (temp_normal) next_state = NORMAL_OP;
            else next_state = COOLING_ACTIVE;
        end
        
        EMERGENCY_STOP: begin
            if (reset_btn) next_state = IDLE;
            else next_state = EMERGENCY_STOP;
        end
        
        default: next_state = IDLE;
    endcase
end

// State register
always @(posedge clk or posedge rst) begin
    if (rst) current_state <= IDLE;
    else current_state <= next_state;
end

// Output logic
always @(*) begin
    conveyor = 0;
    servo = 0;
    fan = 0;
    warning_light = 0;
    buzzer = 0;
    valve = 0;
    
    case (current_state)
        NORMAL_OP: begin
            conveyor = 1;
            valve = ~high_temp;
        end
        
        METAL_HANDLING: begin
            conveyor = 1;
            servo = 1;
        end
        
        RETURN_NORMAL: begin
            conveyor = 1;
        end
        
        COOLING_ACTIVE: begin
            fan = 1;
            warning_light = 1;
            buzzer = 1;
        end
        
        EMERGENCY_STOP: begin
            warning_light = 1;
            buzzer = 1;
        end
    endcase
end

endmodule

verilog/tb_manufacturing_fsm.v
module tb_manufacturing_fsm;

    reg clk, rst;
    reg metal_detected, high_temp, overcurrent, error;
    reg done, ready, temp_normal, reset_btn, emergency;
    wire conveyor, servo, fan, warning_light, buzzer, valve;

    manufacturing_fsm uut (
        .clk(clk),
        .rst(rst),
        .metal_detected(metal_detected),
        .high_temp(high_temp),
        .overcurrent(overcurrent),
        .error(error),
        .done(done),
        .ready(ready),
        .temp_normal(temp_normal),
        .reset_btn(reset_btn),
        .emergency(emergency),
        .conveyor(conveyor),
        .servo(servo),
        .fan(fan),
        .warning_light(warning_light),
        .buzzer(buzzer),
        .valve(valve)
    );

    // Clock generator
    always #5 clk = ~clk;

    initial begin
        // Dumpfile untuk GTKWave
        $dumpfile("manufacturing_fsm.vcd");
        $dumpvars(0, tb_manufacturing_fsm);

        // Initialize
        clk = 0; rst = 1;
        metal_detected = 0; high_temp = 0; overcurrent = 0; error = 0;
        done = 0; ready = 0; temp_normal = 1; reset_btn = 0; emergency = 0;
        
        #20 rst = 0;
        
        // Test normal operation
        #10 metal_detected = 1;
        #10 metal_detected = 0;
        
        // Test cooling activation
        #10 high_temp = 1;
        #20 temp_normal = 1;
        #10 high_temp = 0;
        
        // Test emergency stop
        #10 emergency = 1;
        #20 reset_btn = 1;
        #10 emergency = 0;
        #10 reset_btn = 0;

        #100 $finish;
    end

    initial begin
        $monitor("T=%t | State=%b | Conv=%b | Servo=%b | Fan=%b | Warn=%b | Buzz=%b",
                 $time, uut.current_state, conveyor, servo, fan, warning_light, buzzer);
    end
endmodule

verilog/manufacturing_fsm.vcd
$date
	Thu Nov 20 23:40:06 2025
$end
$version
	Icarus Verilog
$end
$timescale
	1s
$end
$scope module tb_manufacturing_fsm $end
$var wire 1 ! warning_light $end
$var wire 1 " valve $end
$var wire 1 # servo $end
$var wire 1 $ fan $end
$var wire 1 % conveyor $end
$var wire 1 & buzzer $end
$var reg 1 ' clk $end
$var reg 1 ( done $end
$var reg 1 ) emergency $end
$var reg 1 * error $end
$var reg 1 + high_temp $end
$var reg 1 , metal_detected $end
$var reg 1 - overcurrent $end
$var reg 1 . ready $end
$var reg 1 / reset_btn $end
$var reg 1 0 rst $end
$var reg 1 1 temp_normal $end
$scope module uut $end
$var wire 1 ' clk $end
$var wire 1 ( done $end
$var wire 1 ) emergency $end
$var wire 1 * error $end
$var wire 1 + high_temp $end
$var wire 1 , metal_detected $end
$var wire 1 - overcurrent $end
$var wire 1 . ready $end
$var wire 1 / reset_btn $end
$var wire 1 0 rst $end
$var wire 1 1 temp_normal $end
$var reg 1 & buzzer $end
$var reg 1 % conveyor $end
$var reg 3 2 current_state [2:0] $end
$var reg 1 $ fan $end
$var reg 3 3 next_state [2:0] $end
$var reg 1 # servo $end
$var reg 1 " valve $end
$var reg 1 ! warning_light $end
$upscope $end
$upscope $end
$enddefinitions $end
#0
$dumpvars
b1 3
b0 2
11
10
0/
0.
0-
0,
0+
0*
0)
0(
0'
0&
0%
0$
0#
0"
0!
$end
#5
1'
#10
0'
#15
1'
#20
0'
00
#25
1"
1%
b1 2
1'
#30
b10 3
0'
1,
#35
1#
0"
1%
b10 2
1'
#40
0'
0,
#45
1'
#50
1#
1%
b100 3
0'
1+
#55
1&
1!
1$
0#
0%
b1 3
b100 2
1'
#60
0'
#65
1%
0&
0!
0$
b100 3
b1 2
1'
#70
0'
#75
1&
1!
1$
0%
b1 3
b100 2
1'
#80
1&
1!
1$
0'
0+
#85
1"
1%
0&
0!
0$
b1 2
1'
#90
b101 3
0'
1)
#95
1&
1!
0"
0%
b101 2
1'
#100
0'
#105
1'
#110
b0 3
0'
1/
#115
0&
0!
b101 3
b0 2
1'
#120
b1 3
0'
0)
#125
1"
1%
b1 2
1'
#130
0'
0/
